galaxy/kernel/__init__.py
galaxy/kernel/constant.py
galaxy/kernel/kernel.py
galaxy/kernel/loop.py
galaxy/kernel/shell.py
galaxy_py_kernel-0.0.3.dist-info/AUTHORS
galaxy_py_kernel-0.0.3.dist-info/COPYING.md
galaxy_py_kernel-0.0.3.dist-info/LICENSE.txt
galaxy_py_kernel-0.0.3.dist-info/METADATA
galaxy_py_kernel-0.0.3.dist-info/WHEEL
galaxy_py_kernel-0.0.3.dist-info/RECORD
