Metadata-Version: 2.3
Name: galaxy-py-kernel
Version: 0.0.3
Summary: Python Kernel for the Galaxy Project
License: Apache-2.0
Keywords: galaxy,galaxy-kernel
Author: Bastien Saltel
Author-email: bastien.saltel@gmail.com
Maintainer: Bastien Saltel
Maintainer-email: bastien.saltel@gmail.com
Requires-Python: >=3.10
Classifier: Development Status :: 3 - Alpha
Classifier: Programming Language :: Python :: 3
Classifier: Operating System :: OS Independent
Requires-Dist: galaxy-py-service
Requires-Dist: galaxy-py-utils
Requires-Dist: ipykernel
Requires-Dist: jupyter_client
Requires-Dist: tornado
Requires-Dist: transitions
Requires-Dist: uvloop
Project-URL: Changelog, https://github.com/bsaltel/galaxy-py-kernel/blob/main/CHANGELOG.md
Project-URL: Documentation, https://github.com/bsaltel/galaxy-py-kernel
Project-URL: Homepage, https://github.com/bsaltel/galaxy-py-kernel
Project-URL: Issues, https://github.com/bsaltel/galaxy-py-kernel/issues
Project-URL: Repository, https://github.com/bsaltel/galaxy-py-kernel.git
